Arithcal/__init__.py
Arithcal/calc.py
Arithcal-0.1.dist-info/LICENCE.txt
Arithcal-0.1.dist-info/METADATA
Arithcal-0.1.dist-info/WHEEL
Arithcal-0.1.dist-info/top_level.txt
Arithcal-0.1.dist-info/RECORD
