Metadata-Version: 2.1
Name: Arithcal
Version: 0.1
Summary: A small example package
Home-page: https://github.com/vikash130795/Arithcal
Author: Vikash Singh
Author-email: Vikash Singh <vikash@ineuron.ai>
License: UNKNOWN
Project-URL: Homepage, https://github.com/vikash130795/Arithcal
Platform: UNKNOWN
Classifier: Programming Language :: Python :: 3
Classifier: License :: OSI Approved :: MIT License
Classifier: Operating System :: OS Independent
Requires-Python: >=3.7
License-File: LICENCE.txt
